temporalloop/__init__.py
temporalloop/client.py
temporalloop/config.py
temporalloop/config_loader.py
temporalloop/importer.py
temporalloop/logutils.py
temporalloop/main.py
temporalloop/schedule.py
temporalloop/utils.py
temporalloop/worker.py
temporalloop/cmd/__init__.py
temporalloop/cmd/looper.py
temporalloop/cmd/scheduler.py
temporalloop/converters/pydantic.py
temporalloop/interceptors/sentry.py
temporalloop-0.2.2.dist-info/METADATA
temporalloop-0.2.2.dist-info/WHEEL
temporalloop-0.2.2.dist-info/entry_points.txt
temporalloop-0.2.2.dist-info/licenses/LICENSE
temporalloop-0.2.2.dist-info/RECORD
