Metadata-Version: 2.4
Name: temporalloop
Version: 0.2.2
Author-email: ant31 <2t.antoine@gmail.com>
License-File: LICENSE
Requires-Python: <4,>=3.12
Requires-Dist: ant31box[all]>=0.2.8
Requires-Dist: asyncio
Requires-Dist: click
Requires-Dist: pydantic
Requires-Dist: pydantic-settings
Requires-Dist: pyyaml
Requires-Dist: sentry-sdk
Requires-Dist: temporalio[opentelemetry]
